{
    "@id": "http://schema.org/RegisterAction",
    "name": "RegisterAction",
    "description": "The act of registering to be a user of a service, product or web page.",
    "title": "RegisterAction",
    "abstract": false,
    "sealed": false,
    "inherits": "InteractAction",
    "version": "1.0",
    "fields": [],
    "privileges": [
        {
            "mask": 15,
            "type": "global"
        },
        {
            "mask": 15,
            "type": "global",
            "account": "Administrators"
        }
    ]
}
